Simulation/config.v
`define pretrained  // To trigger the $readmemh
`define numLayers 3  // 3 layes in the MLP

`define DataWidth 32 // 32 bit for precision
`define weightWidth 8
`define inputWidth 8

// LAYER 1
`define numWeightLayer1 784 
`define numNeuronLayer1 128   //Check !
`define Layer1ActType "relu" 

// LAYER 2 
`define numWeightLayer2 128
`define numNeuronLayer2 10   //Check !
`define Layer2ActType "hardmax" 

`define weightIntWidth 1  // 1 bit for integer part

Simulation/layer2.v
`include "config.v"

module layer2 (
    input clk,
    input rst, 
    input signed [`DataWidth-1:0] feature_in,
    input [6:0] addr, 
    output reg [`numNeuronLayer2 * 48 - 1 : 0] layer_out 
);

    reg signed [`weightWidth-1:0] weight_matrix [0:(`numWeightLayer2 * `numNeuronLayer2)-1]; // Weight matrix for Layer 1
    reg signed [48-1:0] accumulators [0:`numNeuronLayer2-1]; // Accumulators for each neuron
    reg signed [`DataWidth-1:0] bias_mem [0:`numNeuronLayer2-1];


    initial begin // Fixed: Wrapped in initial block
        $readmemh("weights/fc2_weight.hex", weight_matrix);
        $readmemh("weights/fc2_bias.hex", bias_mem);
    end

    integer n;
    always @(posedge clk) begin
        if (rst) begin
            for (n = 0; n < `numNeuronLayer2; n = n + 1) accumulators[n] <= bias_mem[n];;
        end else begin
            for (n = 0; n < `numNeuronLayer2; n = n + 1) begin
                accumulators[n] <= accumulators[n] + (feature_in * weight_matrix[(n * `numWeightLayer2) + addr]);
            end
        end
    end

    integer k;
    always @(*) begin
        for (k = 0; k < `numNeuronLayer2; k = k + 1) begin
            layer_out[k*48 +: 48] = accumulators[k];
        end
    end


endmodule

Simulation/layer1.v
`include "config.v"

module layer1 (
    input clk,
    input rst, 
    input [`inputWidth-1:0] pixel_in, //Feeding one pixel at a time 
    input [9:0] addr, // Address to access weights (0 to 783 for 28x28 image)
    output reg [`numNeuronLayer1 * `DataWidth - 1 : 0] layer_out //Output Layer 1 
);

    reg signed [`weightWidth-1:0] weight_matrix [0:(`numWeightLayer1 * `numNeuronLayer1)-1]; // Weight matrix for Layer 1
    reg signed [`DataWidth-1:0] accumulators [0:`numNeuronLayer1-1]; // Accumulators for each neuron
    reg signed [`DataWidth-1:0] bias_mem [0:`numNeuronLayer1-1];
    initial begin
    $readmemh("weights/fc1_weight.hex", weight_matrix);
    $readmemh("weights/fc1_bias.hex", bias_mem);
    end
    integer n;
    always @(posedge clk)  begin
        if (rst) begin
            for (n = 0; n < `numNeuronLayer1; n = n + 1) begin
                accumulators[n] <= bias_mem[n];
            end
        end else begin
            for (n = 0; n < `numNeuronLayer1; n = n + 1) begin
                accumulators[n] <= accumulators[n] + ($signed({1'b0, pixel_in}) * weight_matrix[(n * `numWeightLayer1) + addr]);
            end
        end
    end

    integer k;
    always @(*) begin
        for (k = 0; k < `numNeuronLayer1; k = k + 1) begin
            if (accumulators[k][`DataWidth-1] == 1'b1)
                layer_out[k*`DataWidth +: `DataWidth] = 0;
            else
                layer_out[k*`DataWidth +: `DataWidth] = accumulators[k];
        end
    end

endmodule

Simulation/top.v
//========================================
//Project: Hardware Accelerated Neural Network for 28x28 MNIST MLP
//GitHub: DhiaKessad
//========================================

`include "config.v"

module top(
    input wire clk,
    input rst,
    input [7:0] pixel_in,
    input [9:0] l1_addr,    // 0-783
    input [6:0] l2_addr,    // 0-127
    input l2_en,
    output reg [3:0] digit_out,
    output [479:0] final_out
);
    wire [`numNeuronLayer1 * `DataWidth - 1 : 0] l1_parallel_out; // 1D array for simplicity in serialization
    wire [479 : 0] l2_raw_out; // serial
    reg signed [`DataWidth-1:0] l1_serialized_feature;
    assign final_out = l2_raw_out;


//========================================
//28*28=784 pixels input to the 128 neuron layer 1 (total 28*28*784 weight)
//========================================

    layer1 uut1 (
        .clk(clk),
        .rst(rst),
        .pixel_in(pixel_in),
        .addr(l1_addr),
        .layer_out(l1_parallel_out)
    );

    //FSM: 32 bit output to 48 bit for layer 2
    always @(*) begin
        l1_serialized_feature = l1_parallel_out[l2_addr * `DataWidth +: `DataWidth];
    end

//========================================
//10 output neuron with 128 input for each
//========================================

    layer2 uut2 (
        .clk(clk),
        .rst(rst | !l2_en),
        .feature_in(l1_serialized_feature),
        .addr(l2_addr),
        .layer_out(l2_raw_out)
    );

    // Finding the neuron with the biggest value: The prediction of the model
    integer i;
    reg signed [47:0] max_val;
    always @(*) begin
        max_val = $signed(l2_raw_out[0 +: 48]);
        digit_out = 0;
        for (i = 1; i < 10; i = i + 1) begin
            if ($signed(l2_raw_out[i*48 +: 48]) > max_val) begin
                max_val = l2_raw_out[i*48 +: 48];
                digit_out = i;
            end
        end
    end

endmodule

Simulation/tb_top.v
`timescale 1ns/1ps
`include "config.v"

module tb_top();
    reg clk, rst, l2_en;
    reg [7:0] image_mem [0:783];
    reg [9:0] l1_addr;
    reg [6:0] l2_addr;
    wire [3:0] final_digit;

    // Instantiate the FULL system
    top uut (
        .clk(clk),
        .rst(rst),
        .pixel_in(image_mem[l1_addr]),
        .l1_addr(l1_addr),
        .l2_addr(l2_addr),
        .l2_en(l2_en),
        .digit_out(final_digit)
    );

    always #2.5 clk = ~clk; // 200MHz

    initial begin
        // 1. Load data
        $readmemh("tests/image.hex", image_mem);
        clk = 0; rst = 1; l2_en = 0; l1_addr = 0; l2_addr = 0;
        
        $dumpfile("simulation_full.vcd");
        $dumpvars(0, tb_top);

        // 2. RUN LAYER 1 (784 cycles)
        #20 rst = 0;
        repeat (783) begin
            @(posedge clk);
            l1_addr <= l1_addr + 1;
        end
        @(posedge clk); 
        l1_addr <= 783; // Hold last pixel

        // 3. RUN LAYER 2 (128 cycles)
        // We tell the top module to start feeding L1 results to L2
        l2_en = 1; 
        repeat (127) begin
            @(posedge clk);
            l2_addr <= l2_addr + 1;
        end
        @(posedge clk);
        l2_addr <= 127;

        // 4. Final Result
        #100;
        $display("--------------------------------------");
        $display("THE NETWORK PREDICTS THE DIGIT IS: %d", final_digit);
        $display("--------------------------------------");
        $finish;
    end
endmodule

Simulation/simulation_full.vcd
$date
	Mon Dec 29 22:26:25 2025
$end
$version
	Icarus Verilog
$end
$timescale
	1ps
$end
$scope module tb_top $end
$var wire 4 ! final_digit [3:0] $end
$var reg 1 " clk $end
$var reg 10 # l1_addr [9:0] $end
$var reg 7 $ l2_addr [6:0] $end
$var reg 1 % l2_en $end
$var reg 1 & rst $end
$scope module uut $end
$var wire 1 " clk $end
$var wire 480 ' final_out [479:0] $end
$var wire 10 ( l1_addr [9:0] $end
$var wire 7 ) l2_addr [6:0] $end
$var wire 1 % l2_en $end
$var wire 8 * pixel_in [7:0] $end
$var wire 1 & rst $end
$var wire 480 + l2_raw_out [479:0] $end
$var wire 4096 , l1_parallel_out [4095:0] $end
$var reg 4 - digit_out [3:0] $end
$var reg 32 . l1_serialized_feature [31:0] $end
$var reg 48 / max_val [47:0] $end
$var integer 32 0 i [31:0] $end
$scope module uut1 $end
$var wire 10 1 addr [9:0] $end
$var wire 1 " clk $end
$var wire 8 2 pixel_in [7:0] $end
$var wire 1 & rst $end
$var reg 4096 3 layer_out [4095:0] $end
$var integer 32 4 k [31:0] $end
$var integer 32 5 n [31:0] $end
$upscope $end
$scope module uut2 $end
$var wire 7 6 addr [6:0] $end
$var wire 1 " clk $end
$var wire 32 7 feature_in [31:0] $end
$var wire 1 8 rst $end
$var reg 480 9 layer_out [479:0] $end
$var integer 32 : k [31:0] $end
$var integer 32 ; n [31:0] $end
$upscope $end
$upscope $end
$upscope $end
$enddefinitions $end
$comment Show the parameter values. $end
$dumpall
$end
#0
$dumpvars
bx ;
bx :
bx 9
18
bx 7
b0 6
bx 5
bx 4
bx 3
b0 2
b0 1
bx 0
bx /
bx .
bx -
bx ,
bx +
b0 *
b0 )
b0 (
bx '
1&
0%
b0 $
b0 #
0"
bx !
$end
#2500
b0 .
b0 7
b1010 0
b100 !
b100 -
b100000 /
b1000100000000000000000000000000000000000000000000000000000000001011100000000000000000000000000000000000000000000000000000000000000000000000000000000000000000000100100000000000000000000000000010101100000000000000000000000000010011000000000000000000000000000000000000000000000000000000000000100100000000000000000000000000100011000000000000000000000000000110000000000000000000000000000000000000000000000000000000000000100100000000000000000000000000000101010000000000000000000000000000010000000000000000000000000000001010000000000000000000000000000101110000000000000000000000000000000000000000000000000000000000000000000000000000000000000000000111010000000000000000000000000001000000000000000000000000000000000000000000000000000000000000000101110000000000000000000000000001010000000000000000000000000000010010000000000000000000000000000000000000000000000000000000000001010100000000000000000000000000001011000000000000000000000000000000000000000000000000000000000000110100000000000000000000000000010001000000000000000000000000000011100000000000000000000000000011000000000000000000000000000000010100000000000000000000000000000000000000000000000000000000000001000000000000000000000000000000000000000000000000000000000000000111010000000000000000000000000000000000000000000000000000000000000000000000000000000000000000000100110000000000000000000000000000000000000000000000000000000000000000000000000000000000000000000000000000000000000000000000000000000000000000000000000000000000000000000000000000000000000000000011100000000000000000000000000000000000000000000000000000000000000000000000000000000000000000000010100000000000000000000000000000000000000000000000000000000000000000000000000000000000000000000000000000000000000000000000000000000100000000000000000000000000000000000000000000000000000000000000000000000000000000000000000000000000000000000000000000000000000011000000000000000000000000000011000000000000000000000000000000101000000000000000000000000000000001000000000000000000000000001010100000000000000000000000000000101100000000000000000000000000001000000000000000000000000000000000000000000000000000000000000010111000000000000000000000000000101000000000000000000000000000000000000000000000000000000000000010111100000000000000000000000000000000000000000000000000000000000011000000000000000000000000000000000000000000000000000000000000100111000000000000000000000000000001110000000000000000000000000010000000000000000000000000000000010101000000000000000000000000000000000000000000000000000000000000111000000000000000000000000000000001000000000000000000000000000000000000000000000000000000000010000000000000000000000000000000001011000000000000000000000000000011110000000000000000000000000000000000000000000000000000000000000000000000000000000000000000000000000000000000000000000000000010110100000000000000000000000000000000000000000000000000000000000000000000000000000000000000000000001000000000000000000000000000001011000000000000000000000000001111010000000000000000000000000011100100000000000000000000000000000111000000000000000000000000000000000000000000000000000000000001101100000000000000000000000000011101000000000000000000000000000111110000000000000000000000000000000000000000000000000000000000000110000000000000000000000000000100100000000000000000000000000000000000000000000000000000000000100110000000000000000000000000000101010000000000000000000000000001101000000000000000000000000000000010000000000000000000000000001001010000000000000000000000000011101000000000000000000000000000011011000000000000000000000000000010010000000000000000000000000000000000000000000000000000000000010001000000000000000000000000000011100000000000000000000000000001011000000000000000000000000000111011000000000000000000000000000011100000000000000000000000000000000000000000000000000000000000001100000000000000000000000000000000000000000000000000000000000000000000000000000000000000000000000000000000000000000000000000000000000000000000000000000000000010001000000000000000000000000000000000000000000000000000000000000100000000000000000000000000000000101000000000000000000000000000000000 ,
b1000100000000000000000000000000000000000000000000000000000000001011100000000000000000000000000000000000000000000000000000000000000000000000000000000000000000000100100000000000000000000000000010101100000000000000000000000000010011000000000000000000000000000000000000000000000000000000000000100100000000000000000000000000100011000000000000000000000000000110000000000000000000000000000000000000000000000000000000000000100100000000000000000000000000000101010000000000000000000000000000010000000000000000000000000000001010000000000000000000000000000101110000000000000000000000000000000000000000000000000000000000000000000000000000000000000000000111010000000000000000000000000001000000000000000000000000000000000000000000000000000000000000000101110000000000000000000000000001010000000000000000000000000000010010000000000000000000000000000000000000000000000000000000000001010100000000000000000000000000001011000000000000000000000000000000000000000000000000000000000000110100000000000000000000000000010001000000000000000000000000000011100000000000000000000000000011000000000000000000000000000000010100000000000000000000000000000000000000000000000000000000000001000000000000000000000000000000000000000000000000000000000000000111010000000000000000000000000000000000000000000000000000000000000000000000000000000000000000000100110000000000000000000000000000000000000000000000000000000000000000000000000000000000000000000000000000000000000000000000000000000000000000000000000000000000000000000000000000000000000000000011100000000000000000000000000000000000000000000000000000000000000000000000000000000000000000000010100000000000000000000000000000000000000000000000000000000000000000000000000000000000000000000000000000000000000000000000000000000100000000000000000000000000000000000000000000000000000000000000000000000000000000000000000000000000000000000000000000000000000011000000000000000000000000000011000000000000000000000000000000101000000000000000000000000000000001000000000000000000000000001010100000000000000000000000000000101100000000000000000000000000001000000000000000000000000000000000000000000000000000000000000010111000000000000000000000000000101000000000000000000000000000000000000000000000000000000000000010111100000000000000000000000000000000000000000000000000000000000011000000000000000000000000000000000000000000000000000000000000100111000000000000000000000000000001110000000000000000000000000010000000000000000000000000000000010101000000000000000000000000000000000000000000000000000000000000111000000000000000000000000000000001000000000000000000000000000000000000000000000000000000000010000000000000000000000000000000001011000000000000000000000000000011110000000000000000000000000000000000000000000000000000000000000000000000000000000000000000000000000000000000000000000000000010110100000000000000000000000000000000000000000000000000000000000000000000000000000000000000000000001000000000000000000000000000001011000000000000000000000000001111010000000000000000000000000011100100000000000000000000000000000111000000000000000000000000000000000000000000000000000000000001101100000000000000000000000000011101000000000000000000000000000111110000000000000000000000000000000000000000000000000000000000000110000000000000000000000000000100100000000000000000000000000000000000000000000000000000000000100110000000000000000000000000000101010000000000000000000000000001101000000000000000000000000000000010000000000000000000000000001001010000000000000000000000000011101000000000000000000000000000011011000000000000000000000000000010010000000000000000000000000000000000000000000000000000000000010001000000000000000000000000000011100000000000000000000000000001011000000000000000000000000000111011000000000000000000000000000011100000000000000000000000000000000000000000000000000000000000001100000000000000000000000000000000000000000000000000000000000000000000000000000000000000000000000000000000000000000000000000000000000000000000000000000000000010001000000000000000000000000000000000000000000000000000000000000100000000000000000000000000000000101000000000000000000000000000000000 3
b10000000 4
b10011000000000000000000000000000000000000000000000000000000000000000000000000000000000000000000000100000000000000000000000000000000000000000000000010000000000000000000000000000000000000000000001100000000000000000000000000000000000000000000100000111111111111111111111111111111111111111111011110000000000000000000000000000000000000000000000010000000000000000000000000000000000000000000010000111111111111111111111111111111111111111111110010 '
b10011000000000000000000000000000000000000000000000000000000000000000000000000000000000000000000000100000000000000000000000000000000000000000000000010000000000000000000000000000000000000000000001100000000000000000000000000000000000000000000100000111111111111111111111111111111111111111111011110000000000000000000000000000000000000000000000010000000000000000000000000000000000000000000010000111111111111111111111111111111111111111111110010 +
b10011000000000000000000000000000000000000000000000000000000000000000000000000000000000000000000000100000000000000000000000000000000000000000000000010000000000000000000000000000000000000000000001100000000000000000000000000000000000000000000100000111111111111111111111111111111111111111111011110000000000000000000000000000000000000000000000010000000000000000000000000000000000000000000010000111111111111111111111111111111111111111111110010 9
b1010 :
b10000000 5
b1010 ;
1"
#5000
0"
#7500
b1010 ;
b10000000 5
1"
#10000
0"
#12500
b10000000 5
b1010 ;
1"
#15000
0"
#17500
b1010 ;
b10000000 5
1"
#20000
0"
0&
#22500
b1 #
b1 (
b1 1
b10000000 5
b1010 ;
1"
#25000
0"
#27500
b10 #
b10 (
b10 1
b1010 ;
b10000000 5
1"
#30000
0"
#32500
b11 #
b11 (
b11 1
b10000000 5
b1010 ;
1"
#35000
0"
#37500
b100 #
b100 (
b100 1
b1010 ;
b10000000 5
1"
#40000
0"
#42500
b101 #
b101 (
b101 1
b10000000 5
b1010 ;
1"
#45000
0"
#47500
b110 #
b110 (
b110 1
b1010 ;
b10000000 5
1"
#50000
0"
#52500
b111 #
b111 (
b111 1
b10000000 5
b1010 ;
1"
#55000
0"
#57500
b1000 #
b1000 (
b1000 1
b1010 ;
b10000000 5
1"
#60000
0"
#62500
b1001 #
b1001 (
b1001 1
b10000000 5
b1010 ;
1"
#65000
0"
#67500
b1010 #
b1010 (
b1010 1
b1010 ;
b10000000 5
1"
#70000
0"
#72500
b1011 #
b1011 (
b1011 1
b10000000 5
b1010 ;
1"
#75000
0"
#77500
b1100 #
b1100 (
b1100 1
b1010 ;
b10000000 5
1"
#80000
0"
#82500
b1101 #
b1101 (
b1101 1
b10000000 5
b1010 ;
1"
#85000
0"
#87500
b1110 #
b1110 (
b1110 1
b1010 ;
b10000000 5
1"
#90000
0"
#92500
b1111 #
b1111 (
b1111 1
b10000000 5
b1010 ;
1"
#95000
0"
#97500
b10000 #
b10000 (
b10000 1
b1010 ;
b10000000 5
1"
#100000
0"
#102500
b10001 #
b10001 (
b10001 1
b10000000 5
b1010 ;
1"
#105000
0"
#107500
b10010 #
b10010 (
b10010 1
b1010 ;
b10000000 5
1"
#110000
0"
#112500
b10011 #
b10011 (
b10011 1
b10000000 5
b1010 ;
1"
#115000
0"
#117500
b10100 #
b10100 (
b10100 1
b1010 ;
b10000000 5
1"
#120000
0"
#122500
b10101 #
b10101 (
b10101 1
b10000000 5
b1010 ;
1"
#125000
0"
#127500
b10110 #
b10110 (
b10110 1
b1010 ;
b10000000 5
1"
#130000
0"
#132500
b10111 #
b10111 (
b10111 1
b10000000 5
b1010 ;
1"
#135000
0"
#137500
b11000 #
b11000 (
b11000 1
b1010 ;
b10000000 5
1"
#140000
0"
#142500
b11001 #
b11001 (
b11001 1
b10000000 5
b1010 ;
1"
#145000
0"
#147500
b11010 #
b11010 (
b11010 1
b1010 ;
b10000000 5
1"
#150000
0"
#152500
b11011 #
b11011 (
b11011 1
b10000000 5
b1010 ;
1"
#155000
0"
#157500
b11100 #
b11100 (
b11100 1
b1010 ;
b10000000 5
1"
#160000
0"
#162500
b11101 #
b11101 (
b11101 1
b10000000 5
b1010 ;
1"
#165000
0"
#167500
b11110 #
b11110 (
b11110 1
b1010 ;
b10000000 5
1"
#170000
0"
#172500
b11111 #
b11111 (
b11111 1
b10000000 5
b1010 ;
1"
#175000
0"
#177500
b100000 #
b100000 (
b100000 1
b1010 ;
b10000000 5
1"
#180000
0"
#182500
b100001 #
b100001 (
b100001 1
b10000000 5
b1010 ;
1"
#185000
0"
#187500
b100010 #
b100010 (
b100010 1
b1010 ;
b10000000 5
1"
#190000
0"
#192500
b100011 #
b100011 (
b100011 1
b10000000 5
b1010 ;
1"
#195000
0"
#197500
b100100 #
b100100 (
b100100 1
b1010 ;
b10000000 5
1"
#200000
0"
#202500
b100101 #
b100101 (
b100101 1
b10000000 5
b1010 ;
1"
#205000
0"
#207500
b100110 #
b100110 (
b100110 1
b1010 ;
b10000000 5
1"
#210000
0"
#212500
b100111 #
b100111 (
b100111 1
b10000000 5
b1010 ;
1"
#215000
0"
#217500
b101000 #
b101000 (
b101000 1
b1010 ;
b10000000 5
1"
#220000
0"
#222500
b101001 #
b101001 (
b101001 1
b10000000 5
b1010 ;
1"
#225000
0"
#227500
b101010 #
b101010 (
b101010 1
b1010 ;
b10000000 5
1"
#230000
0"
#232500
b101011 #
b101011 (
b101011 1
b10000000 5
b1010 ;
1"
#235000
0"
#237500
b101100 #
b101100 (
b101100 1
b1010 ;
b10000000 5
1"
#240000
0"
#242500
b101101 #
b101101 (
b101101 1
b10000000 5
b1010 ;
1"
#245000
0"
#247500
b101110 #
b101110 (
b101110 1
b1010 ;
b10000000 5
1"
#250000
0"
#252500
b101111 #
b101111 (
b101111 1
b10000000 5
b1010 ;
1"
#255000
0"
#257500
b110000 #
b110000 (
b110000 1
b1010 ;
b10000000 5
1"
#260000
0"
#262500
b110001 #
b110001 (
b110001 1
b10000000 5
b1010 ;
1"
#265000
0"
#267500
b110010 #
b110010 (
b110010 1
b1010 ;
b10000000 5
1"
#270000
0"
#272500
b110011 #
b110011 (
b110011 1
b10000000 5
b1010 ;
1"
#275000
0"
#277500
b110100 #
b110100 (
b110100 1
b1010 ;
b10000000 5
1"
#280000
0"
#282500
b110101 #
b110101 (
b110101 1
b10000000 5
b1010 ;
1"
#285000
0"
#287500
b110110 #
b110110 (
b110110 1
b1010 ;
b10000000 5
1"
#290000
0"
#292500
b110111 #
b110111 (
b110111 1
b10000000 5
b1010 ;
1"
#295000
0"
#297500
b111000 #
b111000 (
b111000 1
b1010 ;
b10000000 5
1"
#300000
0"
#302500
b111001 #
b111001 (
b111001 1
b10000000 5
b1010 ;
1"
#305000
0"
#307500
b111010 #
b111010 (
b111010 1
b1010 ;
b10000000 5
1"
#310000
0"
#312500
b111011 #
b111011 (
b111011 1
b10000000 5
b1010 ;
1"
#315000
0"
#317500
b111100 #
b111100 (
b111100 1
b1010 ;
b10000000 5
1"
#320000
0"
#322500
b111101 #
b111101 (
b111101 1
b10000000 5
b1010 ;
1"
#325000
0"
#327500
b111110 #
b111110 (
b111110 1
b1010 ;
b10000000 5
1"
#330000
0"
#332500
b111111 #
b111111 (
b111111 1
b10000000 5
b1010 ;
1"
#335000
0"
#337500
b1000000 #
b1000000 (
b1000000 1
b1010 ;
b10000000 5
1"
#340000
0"
#342500
b1000001 #
b1000001 (
b1000001 1
b10000000 5
b1010 ;
1"
#345000
0"
#347500
b1000010 #
b1000010 (
b1000010 1
b1010 ;
b10000000 5
1"
#350000
0"
#352500
b1000011 #
b1000011 (
b1000011 1
b10000000 5
b1010 ;
1"
#355000
0"
#357500
b1000100 #
b1000100 (
b1000100 1
b1010 ;
b10000000 5
1"
#360000
0"
#362500
b1000101 #
b1000101 (
b1000101 1
b10000000 5
b1010 ;
1"
#365000
0"
#367500
b1000110 #
b1000110 (
b1000110 1
b1010 ;
b10000000 5
1"
#370000
0"
#372500
b1000111 #
b1000111 (
b1000111 1
b10000000 5
b1010 ;
1"
#375000
0"
#377500
b1001000 #
b1001000 (
b1001000 1
b1010 ;
b10000000 5
1"
#380000
0"
#382500
b1001001 #
b1001001 (
b1001001 1
b10000000 5
b1010 ;
1"
#385000
0"
#387500
b1001010 #
b1001010 (
b1001010 1
b1010 ;
b10000000 5
1"
#390000
0"
#392500
b1001011 #
b1001011 (
b1001011 1
b10000000 5
b1010 ;
1"
#395000
0"
#397500
b1001100 #
b1001100 (
b1001100 1
b1010 ;
b10000000 5
1"
#400000
0"
#402500
b1001101 #
b1001101 (
b1001101 1
b10000000 5
b1010 ;
1"
#405000
0"
#407500
b1001110 #
b1001110 (
b1001110 1
b1010 ;
b10000000 5
1"
#410000
0"
#412500
b1001111 #
b1001111 (
b1001111 1
b10000000 5
b1010 ;
1"
#415000
0"
#417500
b1010000 #
b1010000 (
b1010000 1
b1010 ;
b10000000 5
1"
#420000
0"
#422500
b1010001 #
b1010001 (
b1010001 1
b10000000 5
b1010 ;
1"
#425000
0"
#427500
b1010010 #
b1010010 (
b1010010 1
b1010 ;
b10000000 5
1"
#430000
0"
#432500
b1010011 #
b1010011 (
b1010011 1
b10000000 5
b1010 ;
1"
#435000
0"
#437500
b1010100 #
b1010100 (
b1010100 1
b1010 ;
b10000000 5
1"
#440000
0"
#442500
b1010101 #
b1010101 (
b1010101 1
b10000000 5
b1010 ;
1"
#445000
0"
#447500
b1010110 #
b1010110 (
b1010110 1
b1010 ;
b10000000 5
1"
#450000
0"
#452500
b1010111 #
b1010111 (
b1010111 1
b10000000 5
b1010 ;
1"
#455000
0"
#457500
b1011000 #
b1011000 (
b1011000 1
b1010 ;
b10000000 5
1"
#460000
0"
#462500
b1011001 #
b1011001 (
b1011001 1
b10000000 5
b1010 ;
1"
#465000
0"
#467500
b1011010 #
b1011010 (
b1011010 1
b1010 ;
b10000000 5
1"
#470000
0"
#472500
b1011011 #
b1011011 (
b1011011 1
b10000000 5
b1010 ;
1"
#475000
0"
#477500
b1011100 #
b1011100 (
b1011100 1
b1010 ;
b10000000 5
1"
#480000
0"
#482500
b1011101 #
b1011101 (
b1011101 1
b10000000 5
b1010 ;
1"
#485000
0"
#487500
b1011110 #
b1011110 (
b1011110 1
b1010 ;
b10000000 5
1"
#490000
0"
#492500
b1011111 #
b1011111 (
b1011111 1
b10000000 5
b1010 ;
1"
#495000
0"
#497500
b1100000 #
b1100000 (
b1100000 1
b1010 ;
b10000000 5
1"
#500000
0"
#502500
b1100001 #
b1100001 (
b1100001 1
b10000000 5
b1010 ;
1"
#505000
0"
#507500
b1100010 #
b1100010 (
b1100010 1
b1010 ;
b10000000 5
1"
#510000
0"
#512500
b1100011 #
b1100011 (
b1100011 1
b10000000 5
b1010 ;
1"
#515000
0"
#517500
b1100100 #
b1100100 (
b1100100 1
b1010 ;
b10000000 5
1"
#520000
0"
#522500
b1100101 #
b1100101 (
b1100101 1
b10000000 5
b1010 ;
1"
#525000
0"
#527500
b1100110 #
b1100110 (
b1100110 1
b1010 ;
b10000000 5
1"
#530000
0"
#532500
b1100111 #
b1100111 (
b1100111 1
b10000000 5
b1010 ;
1"
#535000
0"
#537500
b1101000 #
b1101000 (
b1101000 1
b1010 ;
b10000000 5
1"
#540000
0"
#542500
b1101001 #
b1101001 (
b1101001 1
b10000000 5
b1010 ;
1"
#545000
0"
#547500
b1101010 #
b1101010 (
b1101010 1
b1010 ;
b10000000 5
1"
#550000
0"
#552500
b1101011 #
b1101011 (
b1101011 1
b10000000 5
b1010 ;
1"
#555000
0"
#557500
b1101100 #
b1101100 (
b1101100 1
b1010 ;
b10000000 5
1"
#560000
0"
#562500
b1101101 #
b1101101 (
b1101101 1
b10000000 5
b1010 ;
1"
#565000
0"
#567500
b1101110 #
b1101110 (
b1101110 1
b1010 ;
b10000000 5
1"
#570000
0"
#572500
b1101111 #
b1101111 (
b1101111 1
b10000000 5
b1010 ;
1"
#575000
0"
#577500
b1110000 #
b1110000 (
b1110000 1
b1010 ;
b10000000 5
1"
#580000
0"
#582500
b1110001 #
b1110001 (
b1110001 1
b10000000 5
b1010 ;
1"
#585000
0"
#587500
b1110010 #
b1110010 (
b1110010 1
b1010 ;
b10000000 5
1"
#590000
0"
#592500
b1110011 #
b1110011 (
b1110011 1
b10000000 5
b1010 ;
1"
#595000
0"
#597500
b1110100 #
b1110100 (
b1110100 1
b1010 ;
b10000000 5
1"
#600000
0"
#602500
b1110101 #
b1110101 (
b1110101 1
b10000000 5
b1010 ;
1"
#605000
0"
#607500
b1110110 #
b1110110 (
b1110110 1
b1010 ;
b10000000 5
1"
#610000
0"
#612500
b1110111 #
b1110111 (
b1110111 1
b10000000 5
b1010 ;
1"
#615000
0"
#617500
b1111000 #
b1111000 (
b1111000 1
b1010 ;
b10000000 5
1"
#620000
0"
#622500
b1111001 #
b1111001 (
b1111001 1
b10000000 5
b1010 ;
1"
#625000
0"
#627500
b1111010 #
b1111010 (
b1111010 1
b1010 ;
b10000000 5
1"
#630000
0"
#632500
b1111011 #
b1111011 (
b1111011 1
b10000000 5
b1010 ;
1"
#635000
0"
#637500
b1111100 #
b1111100 (
b1111100 1
b1010 ;
b10000000 5
1"
#640000
0"
#642500
b1111101 #
b1111101 (
b1111101 1
b10000000 5
b1010 ;
1"
#645000
0"
#647500
b1111110 #
b1111110 (
b1111110 1
b1010 ;
b10000000 5
1"
#650000
0"
#652500
b1111111 #
b1111111 (
b1111111 1
b10000000 5
b1010 ;
1"
#655000
0"
#657500
b10000000 #
b10000000 (
b10000000 1
b1010 ;
b10000000 5
1"
#660000
0"
#662500
b10000001 #
b10000001 (
b10000001 1
b10000000 5
b1010 ;
1"
#665000
0"
#667500
b10000010 #
b10000010 (
b10000010 1
b1010 ;
b10000000 5
1"
#670000
0"
#672500
b10000011 #
b10000011 (
b10000011 1
b10000000 5
b1010 ;
1"
#675000
0"
#677500
b10000100 #
b10000100 (
b10000100 1
b1010 ;
b10000000 5
1"
#680000
0"
#682500
b10000101 #
b10000101 (
b10000101 1
b10000000 5
b1010 ;
1"
#685000
0"
#687500
b10000110 #
b10000110 (
b10000110 1
b1010 ;
b10000000 5
1"
#690000
0"
#692500
b10000111 #
b10000111 (
b10000111 1
b10000000 5
b1010 ;
1"
#695000
0"
#697500
b10001000 #
b10001000 (
b10001000 1
b1010 ;
b10000000 5
1"
#700000
0"
#702500
b10001001 #
b10001001 (
b10001001 1
b10000000 5
b1010 ;
1"
#705000
0"
#707500
b10001010 #
b10001010 (
b10001010 1
b1010 ;
b10000000 5
1"
#710000
0"
#712500
b10001011 #
b10001011 (
b10001011 1
b10000000 5
b1010 ;
1"
#715000
0"
#717500
b10001100 #
b10001100 (
b10001100 1
b1010 ;
b10000000 5
1"
#720000
0"
#722500
b10001101 #
b10001101 (
b10001101 1
b10000000 5
b1010 ;
1"
#725000
0"
#727500
b10001110 #
b10001110 (
b10001110 1
b1010 ;
b10000000 5
1"
#730000
0"
#732500
b10001111 #
b10001111 (
b10001111 1
b10000000 5
b1010 ;
1"
#735000
0"
#737500
b10010000 #
b10010000 (
b10010000 1
b1010 ;
b10000000 5
1"
#740000
0"
#742500
b10010001 #
b10010001 (
b10010001 1
b10000000 5
b1010 ;
1"
#745000
0"
#747500
b10010010 #
b10010010 (
b10010010 1
b1010 ;
b10000000 5
1"
#750000
0"
#752500
b10010011 #
b10010011 (
b10010011 1
b10000000 5
b1010 ;
1"
#755000
0"
#757500
b10010100 #
b10010100 (
b10010100 1
b1010 ;
b10000000 5
1"
#760000
0"
#762500
b10010101 #
b10010101 (
b10010101 1
b10000000 5
b1010 ;
1"
#765000
0"
#767500
b10010110 #
b10010110 (
b10010110 1
b1010 ;
b10000000 5
1"
#770000
0"
#772500
b10010111 #
b10010111 (
b10010111 1
b10000000 5
b1010 ;
1"
#775000
0"
#777500
b10011000 #
b10011000 (
b10011000 1
b1010 ;
b10000000 5
1"
#780000
0"
#782500
b10011001 #
b10011001 (
b10011001 1
b10000000 5
b1010 ;
1"
#785000
0"
#787500
b10011010 #
b10011010 (
b10011010 1
b1010 ;
b10000000 5
1"
#790000
0"
#792500
b10011011 #
b10011011 (
b10011011 1
b10000000 5
b1010 ;
1"
#795000
0"
#797500
b10011100 #
b10011100 (
b10011100 1
b1010 ;
b10000000 5
1"
#800000
0"
#802500
b10011101 #
b10011101 (
b10011101 1
b10000000 5
b1010 ;
1"
#805000
0"
#807500
b10011110 #
b10011110 (
b10011110 1
b1010 ;
b10000000 5
1"
#810000
0"
#812500
b10011111 #
b10011111 (
b10011111 1
b10000000 5
b1010 ;
1"
#815000
0"
#817500
b10100000 #
b10100000 (
b10100000 1
b1010 ;
b10000000 5
1"
#820000
0"
#822500
b10100001 #
b10100001 (
b10100001 1
b10000000 5
b1010 ;
1"
#825000
0"
#827500
b10100010 #
b10100010 (
b10100010 1
b1010 ;
b10000000 5
1"
#830000
0"
